speconsense/__init__.py
speconsense/cli.py
speconsense/msa.py
speconsense/quality_report.py
speconsense/synth.py
speconsense/types.py
speconsense/core/__init__.py
speconsense/core/__main__.py
speconsense/core/cli.py
speconsense/core/clusterer.py
speconsense/core/workers.py
speconsense/profiles/__init__.py
speconsense/profiles/example.yaml
speconsense/profiles/herbarium.yaml
speconsense/profiles/largedata.yaml
speconsense/profiles/nostalgia.yaml
speconsense/profiles/strict.yaml
speconsense/scalability/__init__.py
speconsense/scalability/base.py
speconsense/scalability/config.py
speconsense/scalability/vsearch.py
speconsense/summarize/__init__.py
speconsense/summarize/__main__.py
speconsense/summarize/analysis.py
speconsense/summarize/cli.py
speconsense/summarize/clustering.py
speconsense/summarize/fields.py
speconsense/summarize/io.py
speconsense/summarize/iupac.py
speconsense/summarize/merging.py
speconsense-0.7.2.dist-info/licenses/LICENSE
speconsense-0.7.2.dist-info/METADATA
speconsense-0.7.2.dist-info/WHEEL
speconsense-0.7.2.dist-info/entry_points.txt
speconsense-0.7.2.dist-info/top_level.txt
speconsense-0.7.2.dist-info/RECORD
