Metadata-Version: 2.4
Name: speconsense
Version: 0.7.2
Summary: High-quality clustering and consensus generation for Oxford Nanopore amplicon reads
Author-email: Josh Walker <joshowalker@yahoo.com>
License: BSD-3-Clause
Project-URL: Homepage, https://github.com/joshuaowalker/speconsense
Project-URL: Repository, https://github.com/joshuaowalker/speconsense
Project-URL: Issues, https://github.com/joshuaowalker/speconsense/issues
Keywords: bioinformatics,nanopore,consensus,clustering,amplicon
Classifier: Development Status :: 4 - Beta
Classifier: Intended Audience :: Science/Research
Classifier: Operating System :: OS Independent
Classifier: Programming Language :: Python :: 3
Classifier: Programming Language :: Python :: 3.8
Classifier: Programming Language :: Python :: 3.9
Classifier: Programming Language :: Python :: 3.10
Classifier: Programming Language :: Python :: 3.11
Classifier: Programming Language :: Python :: 3.12
Classifier: Topic :: Scientific/Engineering :: Bio-Informatics
Requires-Python: >=3.8
License-File: LICENSE
Requires-Dist: edlib>=1.3.9
Requires-Dist: numpy>=1.20.0
Requires-Dist: biopython>=1.79
Requires-Dist: tqdm>=4.62.0
Requires-Dist: scipy>=1.7.0
Requires-Dist: adjusted-identity>=0.2.4
Requires-Dist: pyyaml>=5.0
Provides-Extra: dev
Requires-Dist: pytest>=7.0.0; extra == "dev"
Requires-Dist: pytest-cov>=4.0.0; extra == "dev"
Dynamic: license-file
